figer/__init__.py
figer/__main__.py
figer/__version__.py
figer/main.py
figer-1.0.0.dist-info/LICENSE
figer-1.0.0.dist-info/METADATA
figer-1.0.0.dist-info/WHEEL
figer-1.0.0.dist-info/top_level.txt
figer-1.0.0.dist-info/RECORD
