Metadata-Version: 2.1
Name: figer
Version: 1.0.0
Summary: Easily manage config files in multi user environment
Author-email: n4n5 <its.just.n4n5@gmail.com>
License: MIT License
Project-URL: Homepage, https://github.com/its-just-nans/figer
Project-URL: Bug Tracker, https://github.com/its-just-nans/figer/issues
Keywords: figer,config,config-file
Classifier: License :: OSI Approved :: MIT License
Classifier: Programming Language :: Python
Classifier: Programming Language :: Python :: 3
Requires-Python: >=3.6
License-File: LICENSE
